Workbook

Sheet Instrucciones
B1: Plantilla de testing — instrucciones para juniors
B4: Antes de empezar
B5: 1. Lee la hoja "Plan de testing" para saber qué área te toca esta semana.
B6: 2. Antes de reportar un bug, busca en la hoja "Bugs" si ya está reportado. Si lo está, NO crees uno nuevo: añade tu nombre en la columna "Reportado también por" para que sepamos cuánta gente lo ve.
B7: 3. Para reportar, ve a la hoja "Bugs" y rellena UNA fila por bug. No mezcles dos bugs en la misma fila.
B8: 4. Las propuestas de mejora NO son bugs. Van en la hoja "Propuestas de mejora". Si lo mezclas, contaminas la cola de los devs y nos retrasas.
B10: Qué es bug y qué no es
B11: • Bug: el sistema hace algo distinto de lo que debería. Ejemplo: "al crear paciente con email vacío, la pantalla se queda en blanco" → BUG.
B12: • No es bug: el sistema funciona, pero crees que se podría hacer mejor. Ejemplo: "el botón de guardar debería ser más visible" → PROPUESTA DE MEJORA.
B13: • Duda de uso: el sistema funciona, pero no entiendes cómo se usa. Pregunta antes de reportar; no es bug.
B15: Cómo reportar bien (las 3 cosas que importan)
B16: 1. PASOS PARA REPRODUCIR: tan claros que cualquiera pueda seguirlos. Ejemplo: "1) Login como admin. 2) Ir a Pacientes. 3) Crear paciente con nombre vacío. 4) Pulsar Guardar."
... B42: • Cuando el PM marque tu bug como "Arreglado", revisa que efectivamente está arreglado y cámbialo a "Verificado" o reábrelo si no lo está.

Sheet Bugs
A1: 👇 Una fila por bug. Columna A se autocompleta. Borra la fila de ejemplo (fila 3, en gris) cuando empieces a usarla.
A2: ID | B2: Fecha | C2: Tester (código) | D2: Feature | E2: Pasos para reproducir | F2: Qué pasó | G2: Qué esperaba | H2: Captura (link) | I2: Severidad (tester) | J2: Reportado también por | K2: Severidad (PM) | L2: Estado | M2: Duplicado de | N2: Asignado a | O2: Notas internas (PM/dev) | P2: Fecha arreglo
A3: =IF(C2="","","BUG-"&TEXT(ROW()-1,"000")) -> BUG-002 | B3: 2026-05-13 | C3: JUN01 | D3: Sales orders/Facturación | E3: 1) Login como admin. 2) Crear cita para paciente con mutua. 3) Marcar consulta como efectuada. 4) Ir a facturación. | F3: La factura suma dos veces el importe del servicio: aparece 120€ cuando deberían ser 60€. | G3: El importe del servicio debería aparecer una sola vez: 60€. | H3: https://drive.google.com/file/... | I3: Bloqueante | K3: Bloqueante | L3: Arreglado | N3: Dip | O3: Confirmado, mismo bug que el de la reunión del lunes. Test de regresión requerido.
A4: =IF(C3="","","BUG-"&TEXT(ROW()-1,"000")) -> BUG-003 | B4: 46155 | C4: DMT | D4: CRM | E4: 1) Login como admin. 2) Acceder al CRM. 3) Entrar en el apartado de Mail Templates. | F4: La página se queda en blanco y deja de funcionar. | G4: Acceder al apartado de mail templates. | H4: Screenshot_20260514_083951.png | I4: Bloqueante | J4: JUN03, JUN05, Randú, JZO | K4: Bloqueante
A5: =IF(C4="","","BUG-"&TEXT(ROW()-1,"000")) -> BUG-004 | B5: 46155 | C5: DMT | D5: CRM | E5: 1) Login como admin. 2) Acceder al CRM. 3) Entrar en el apartado de Invoices dentro de Marketplace. | F5: La página se queda en blanco y deja de funcionar. | G5: Acceder al apartado de Invoices. | H5: Screenshot_20260514_085235.png | I5: Bloqueante | J5: JUN05, Randú | K5: Menor
A6: =IF(C5="","","BUG-"&TEXT(ROW()-1,"000")) -> BUG-005 | B6: 46156 | C6: DMT | D6: CRM | E6: 1) Login como admin. 2) Acceder a cualquier apartado del CRM. | F6: Los apartados de la barra superior de notificaciones aparecen con un indicador de mensaje/s no leido/s aunque todos estén marcados como leido. | G6: Que al marcar como leido todos los mensajes, desaparezca el indicador. | H6: Screenshot_20260514_085622.png | I6: Menor | K6: Bloqueante | L6: En arreglo
A7: =IF(C6="","","BUG-"&TEXT(ROW()-1,"000")) -> BUG-006 | B7: 46156 | C7: DMT | D7: CRM | E7: 1) Login como admin. 2) Crear un paciente en creación rápida. | F7: Al presionar la tecla ESC o clickar fuera de la ventana, esta realiza una animación de cerrado, pero no se llega a cerrar. | G7: Cerrar la ventana emergente. | H7: Screenshot_20260514_090456.png | I7: Menor | K7: No es bug | L7: No es bug
A8: =IF(C7="","","BUG-"&TEXT(ROW()-1,"000")) -> BUG-007 | B8: 46156 | C8: DMT | D8: CRM | E8: 1) Login como admin. 2) Acceder al CRM. 3) Editar un lead sin cambiar ningun dato. 4) Guardar cambios. | F8: Aunque no haya ningún cambio al editar el lead, se puede guardar los cambios como si hubiera alguno y aparece la ventana de cambios guardados. Tambén pasa en otros módulos del CRM. | G8: No permitir guardar cambios si no hay ninguno realizado | H8: Screenshot_20260514_091734.png | I8: Menor | K8: Menor | L8: Verificado
A9: =IF(C8="","","BUG-"&TEXT(ROW()-1,"000")) -> BUG-008 | B9: 46156 | C9: DMT | D9: CRM | E9: 1) Login como admin. 2) Acceder al CRM. 3) Bajar el rango del lead. | F9: El rango de un lead no tiene límite, por lo que puede llegar a ser negativo. | G9: No permitir bajar el rango de un lead por debajo de cero. | H9: Screenshot_20260514_092655.png | I9: Menor | K9: No es bug | L9: No es bug
A10: =IF(C9="","","BUG-"&TEXT(ROW()-1,"000")) -> BUG-009 | B10: 46156 | C10: DMT | D10: CRM | E10: 1) Login como admin. 2) Acceder al apartado de contactos del CRM. 3) Elegir contacto. | F10: Cualuier usuario tiene acceso a los contactos creados de cualquier otro usuario. | G10: Solo visualizar los contactos del mismo usuario. | H10: Screenshot_20260514_093635.png | I10: Grave | K10: Diferido | L10: Diferido
A11: =IF(C10="","","BUG-"&TEXT(ROW()-1,"000")) -> BUG-010 | B11: 46156 | C11: Randú | D11: CRM | E11: 1) Login como admin. 2) Acceder al CRM. 3) Elegir opción de Dashboard de Marketplace. | F11: No redirige al usuario a ninguna pagina y en general no hace nada. | G11: Que me redirija a un Dashboard. | H11: https://drive.google.com/file/d/1qqBVZUej6lS8O71n8ZLcrwVh4ghafLVO/view?usp=drive_link | I11: Menor | K11: Menor | L11: Verificado
A12: =IF(C11="","","BUG-"&TEXT(ROW()-1,"000")) -> BUG-011 | B12: 46156 | C12: DMT | D12: CRM | E12: 1) Login como admin. 2) Crear una lista. 3) Añadir leads a la lista. 4) Añadir distintos leads a la lista. | F12: Al añadir leads a una lista, reemplazan a los anteriores, en vez de añadirlos. | G12: Añadir a los leads junto a los anteriores. | H12: Screenshot_20260514_094457.png | I12: Grave | K12: Bloqueante | L12: En arreglo
A13: =IF(C12="","","BUG-"&TEXT(ROW()-1,"000")) -> BUG-012 | B13: 46156 | C13: DMT | D13: CRM | E13: 1) Login como admin. 2) Crear una lista de empresas | F13: Es imposible añadir empresas a una lista de empresas, puesto que en ningún apartado se pueden ver o modificar empresas en el CRM. | G13: Encontrar forma de añadir empresas a la lista | H13: Screenshot_20260514_095759.png | I13: Grave | K13: Bloqueante | L13: En arreglo
A14: =IF(C13="","","BUG-"&TEXT(ROW()-1,"000")) -> BUG-013 | B14: 46156 | C14: DMT | D14: CRM | E14: 1) Login como admin. 2) Acceder al apartado de label. 3) Añadir flitros. 4) Resetear filtros. | F14: Los filtros no se resetean a no ser que se cambie de apartado. | G14: Que los filtros se reinicien y se muestren los labels sin filtros. | H14: Screenshot_20260514_100704.png | I14: Menor | K14: Bloqueante | L14: En arreglo
A15: =IF(C14="","","BUG-"&TEXT(ROW()-1,"000")) -> BUG-014 | B15: 46156 | C15: DMT | D15: CRM | E15: 1) Login como admin. 2) Acceder al apartado Activity Process. 3) Crear proceso. 4) Cerrar sin guardar. | F15: La página no se cierra. | G15: La página se debería cerrar. | H15: Screenshot_20260514_100835.png | I15: Menor
A16: =IF(C15="","","BUG-"&TEXT(ROW()-1,"000")) -> BUG-015 | B16: 46156 | C16: 46177 | D16: CRM | E16: 1)Login como admin 2)Acceder al apartado de mercado 3)Crear producto 4)añadir | F16: Cuando queremos añadir una nueva tienda nos dice que tenemos el acceso restringido | G16: Que cree el producto correctamente | H16: https://drive.google.com/file/d/1lmedZyT55g_dk8IBSurOILoN2A-bTnph/view?usp=sharing | I16: Menor | K16: No es bug | L16: No es bug
A17: =IF(C16="","","BUG-"&TEXT(ROW()-1,"000")) -> BUG-016 | B17: 46156 | C17: 46177 | D17: CRM | E17: 1) Login como admin 2) Acceder al apartado Finance 3) Acceder al apartado órdenes 4) Crear nueva Órden | F17: La página se queda cargando los datos de la orden | G17: Cargar la interfaz para añadir la orden y poder añadir una nueva sin ningún error | H17: https://drive.google.com/file/d/1tGW5Ffw0ZowRGWD0rd3FQjz9tE8LoC74/view?usp=sharing | I17: Bloqueante | J17: JUN13, DMT | K17: Menor | L17: Diferido
A18: BUG-017 | B18: 46156 | C18: 46180 | D18: Crear paciente | E18: 1)Login como admin 2)Acceder al apartado clinical Service 3) Acceder al apartado Paciente | F18: No permite crear un nuevo paciente si no creas primero una clínica | G18: Tener opciones de clínicas o permitir añadir después | H18: https://drive.google.com/file/d/1br5eCdTbDq_lK0ZQQifxY4c_6RAumYKl/view?usp=drive_link | I18: Bloqueante | K18: No es bug | L18: No es bug
A19: BUG-018 | B19: 46160 | C19: DMT | D19: CRM | E19: 1) Login como admin. 2) Acceder al apartado de oportunidades del CRM. 3) Crear una oportunidad. 4) Bajar el porcentaje de promesa. | F19: El porcentaje de promesa no tiene límite, por lo que puede llegar a ser negativo o mayor de 100. | G19: Ya que el porcentaje de promesa no debería poder ser negativo, limitar el porcentaje a números positivos entre 0 y 100. | H19: Screenshot_20260518_084155.png | I19: Menor | K19: Menor | L19: Diferido
A20: =IF(C19="","","BUG-"&TEXT(ROW()-1,"000")) -> BUG-019 | B20: 46160 | C20: DMT | D20: CRM | E20: 1) Login como admin. 2) Acceder al apartado de notas del CRM. 3) Crear una nota. | F20: En el apartado de notas no aparece la opción de mandar notificación al usuario, mientras que en el apartado individual de Lead, Tarea o Contacto, sí que lo permite. | G20: Añadir la casilla de marcar notificación. | H20: Screenshot_20260518_085300.png | I20: Menor | K20: Menor | L20: En revisión
A21: =IF(C20="","","BUG-"&TEXT(ROW()-1,"000")) -> BUG-020 | B21: 46160 | C21: DMT | D21: CRM | E21: 1) Login como admin. 2) Acceder a los datos de un Lead. 3) Añadir CV. | F21: El botón de añadir CV es el mismo que el del usuario, por lo que pone "Add your CV". | G21: Cambiar el botón por "Add CV". | H21: Screenshot_20260518_085924.png | I21: Menor | K21: Menor | L21: Diferido
A22: =IF(C21="","","BUG-"&TEXT(ROW()-1,"000")) -> BUG-021 | B22: 46160 | C22: DMT | D22: CRM | E22: 1) Login como admin. 2) Acceder al apartado de notas del CRM. 3) Presionar los 3 puntos para editar nota. | F22: Los datos de título, descripción y marcar como privado no cargan correctamente y hace falta cargar la nota desde Nota Existente. | G22: Cargar los datos correctamente. | H22: Screenshot_20260518_090511.png | I22: Grave | J22: Randú
A23: =IF(C22="","","BUG-"&TEXT(ROW()-1,"000")) -> BUG-022 | B23: 46160 | C23: DMT | D23: CRM | E23: 1) Login como admin. 2) Acceder a los datos de un Lead. 3) Editar nota. 4) Editar nota existente. 5) Editar nota existente. | F23: Se puede editar nota recursivamente de forma infinita. | G23: Si ya estás editando la nota, que no aparezca el botón de editar nota. | H23: Screenshot_20260518_090829.png | I23: Menor
A24: =IF(C23="","","BUG-"&TEXT(ROW()-1,"000")) -> BUG-023 | B24: 46160 | C24: DMT | D24: CRM | E24: 1) Login como admin. 2) Acceder al apartado de notas del CRM. 3) Borrar una o varias notas. | F24: No es posible borrar ninguna nota, debido a que el botón Delete no funciona. | G24: El botón Delete debe permitir borrar la o las notas. | H24: Screenshot_20260518_091310.png | I24: Grave
A25: =IF(C24="","","BUG-"&TEXT(ROW()-1,"000")) -> BUG-024 | B25: 46160 | C25: DMT | D25: Otra | E25: 1) Login como admin. 2) Acceder al apartado de challenges. 3) Añadir un challenge de cualqier tipo. | F25: La página crashea y se queda en blanco. | G25: Acceder a la creación de un challenge. | H25: Screenshot_20260518_091658.png | I25: Bloqueante
A26: =IF(C25="","","BUG-"&TEXT(ROW()-1,"000")) -> BUG-025 | B26: 46160 | C26: DMT | D26: Otra | E26: 1) Login como admin. 2) Acceder al dashboard de Marketplace. | F26: El botón de Dashboad de Marketplace lleva a la página en la que te encuentras. | G26: Acceder al Dashboard de Marketplace. | H26: Screenshot_20260518_092218.png | I26: Grave
A27: =IF(C26="","","BUG-"&TEXT(ROW()-1,"000")) -> BUG-026 | B27: 46160 | C27: DMT | D27: Otra | E27: 1) Login como admin. 2) Acceder al apartado Customer Pricing de marketplace. | F27: La página muestra los productos guardados por otros usuarios. A pesar de no poder crear uno, cualquier usuario puede editar o borrar los productos de otros. | G27: No tener acceso a los productos guardados por otros usuarios. | H27: Screenshot_20260518_093135.png | I27: Grave
A28: =IF(C27="","","BUG-"&TEXT(ROW()-1,"000")) -> BUG-027 | B28: 46160 | C28: DMT | D28: Otra | E28: 1) Login como admin. 2) Acceder al apartado Supplier Pricing de marketplace. | F28: La página muestra los productos guardados por otros usuarios. A pesar de no poder crear uno, cualquier usuario puede editar o borrar los productos de otros. | G28: No tener acceso a los productos guardados por otros usuarios. | H28: Screenshot_20260518_093539.png | I28: Grave
A29: =IF(C28="","","BUG-"&TEXT(ROW()-1,"000")) -> BUG-028 | B29: 46160 | C29: Randú | D29: Otra | E29: 1) Login como admin. 2) Acceder al CRM. 3) Seleccionar un paciente o varios en Clinical service. 4) Elejir la opción de share with doctor de Actions. 5) precionar share sin elegir doctor. | F29: Se bloquea la página y se pone en blanco. | G29: Un aviso de 'no se puede enviar sin un doctor'. | H29: https://drive.google.com/file/d/1hHLwfY8w4Iy469VwfLYvxlAC2GV43_7h/view?usp=drive_link | I29: Bloqueante
A30: =IF(C29="","","BUG-"&TEXT(ROW()-1,"000")) -> BUG-029 | B30: 46160 | C30: JZO | D30: Otra | E30: 1) Login como admin. 2) Acceder al Marketplace. 3) Acceder al apartado tablero | F30: Al seleccionar botón no ejecuta la acción de entrar al tablero. | G30: Poder acceder a la sección del tablero | H30: https://drive.google.com/file/d/1KI-IuNjs34QyMsv-DbwFZnflQJFTTutu/view?usp=sharing | I30: Menor
A31: =IF(C30="","","BUG-"&TEXT(ROW()-1,"000")) -> BUG-030 | B31: 46160 | C31: JZO | D31: Otra | E31: 1) Login como admin. 2) Acceder al Analityc Dashboard. 3) Acceder a Clinic A / Clinic B / Clinic C | F31: Al querer acceder a los supuestos dashboards de las clínicas, te devuelve directamente a la sección de Dashboard principal | G31: Acceder a cada sección de clinica y poder ver sus supuestos tableros | H31: https://drive.google.com/file/d/1XkzQ6F-ZeoTUnoxeDgHVaJhw6ft0N2LX/view?usp=drive_link | I31: Bloqueante
A32: =IF(C31="","","BUG-"&TEXT(ROW()-1,"000")) -> BUG-031 | B32: 46160 | C32: JZO | D32: Otra | E32: 1) Login como admin. 2) Acceder al Faq. 3) Añadir Fag. | F32: El botón de 'Suggested by AI' no ejecuta ninguna función | G32: Que ejecutase alguna acción en la que se pueda ver la funcionalidad de la IA. | H32: https://drive.google.com/file/d/1gGBxNpr6ryk-MDXa1bpHdO5rriUvsG4r/view?usp=drive_link | I32: Menor | J32: JUN06,
A33: =IF(C32="","","BUG-"&TEXT(ROW()-1,"000")) -> BUG-032 | B33: 46160 | C33: 46179 | D33: Otra | E33: 1) Login como admin. 2) Acceder al Clinical Service. 3) Acceder a Recetas. 4) Agregar nueva receta | F33: En el apartado "Other Instructions", el subapartado "Attachments", no carga el documento o imagén subida | G33: Debería cargar la imagén o documento subido y guardarse en el formulario para luego subirlo | H33: https://drive.google.com/file/d/1RwEqdkCnkHkd90w7_YfS87k4UO09d6sS/view?usp=drive_link | I33: Menor
A34: =IF(C33="","","BUG-"&TEXT(ROW()-1,"000")) -> BUG-033 | B34: 46160 | C34: JZO | D34: Otra | E34: 1) Login como admin. 2) Acceder a Finance. 3) Acceder a Subscription. 4) Boton action. 5) Boton Add Label | F34: Los botones "Add Tag" y "Remove Tag" no cumplen con ninguna función | G34: Que pueda añadir tags dandole al botón y poder eliminar los tags que selecciono. | H34: https://drive.google.com/file/d/1_Kw_XXR8lOB4Aco9KS3C0YDALi9L0GSw/view?usp=drive_link | I34: Menor
A35: =IF(C34="","","BUG-"&TEXT(ROW()-1,"000")) -> BUG-034 | B35: 46160 | C35: 46179 | D35: Otra | E35: 1) Login como admin. 2) Acceder al Clinical Service. 3) Acceder a Productos. 4) Agregar nueva producto | F35: En el apartado "Advanced Information", el subapartado "Product Image", carga infinitamente la imagén o documento subido. | G35: Debería cargar la imagén o documento subido y guardarse en el formulario para luego subirlo. (Se completa el formulario) | H35: https://drive.google.com/file/d/15IvnQg9E8RxEAim6FfUZBGql_jlH5LL_/view?usp=drive_link | I35: Menor
A36: =IF(C35="","","BUG-"&TEXT(ROW()-1,"000")) -> BUG-035 | B36: 46160 | C36: RGP | D36: Otra | E36: 1) Login como admin. 2) Acceder a Dashboard/Ecosystem Dashboard. 3) Directory. 4) Filtrar los Ecosystems | F36: El filtrado saca que hay 3 ecosistemas cuando son 2. | G36: Debería cargar el número real, en función del otro filtrado | H36: Captura de pantalla 2026-05-18 123233.png | I36: Menor | J36: Randú
A37: =IF(C36="","","BUG-"&TEXT(ROW()-1,"000")) -> BUG-036 | B37: 46160 | C37: JZO | D37: CRM | E37: 1) Login como admin. 2) Acceder CRM. 3) Acceder a Leads. 4) Crear Lead. 5) Boton de + para añadir compañia. | F37: El boton de "Go back" no tiene funcionalidad de volver. | G37: Deberia poder volver a la pestaña anterior para más fluidez | H37: https://drive.google.com/file/d/1HIp9I1BWQZn2ajV6-FUJX5wxlTXJdZ1V/view?usp=drive_link | I37: Menor
A38: BUG-037 | B38: 46160 | C38: 46177 | D38: CRM | E38: 1)Login como admin 2)Acceder a CRM 3) Acceder a CRM 4)Acceder a lista) 5)Crear Lista | F38: No se muestra la lista que se creo recientemente en la sección de lista del Crm | G38: Debería poder enviar un correo a usuario correctamente | H38: https://drive.google.com/file/d/1eN1MuJPAPMxls8strEmhqkdKcgim8buQ/view?usp=sharing | I38: Menor
A39: =IF(C38="","","BUG-"&TEXT(ROW()-1,"000")) -> BUG-038 | B39: 46160 | C39: RGP | D39: Otra | E39: 1) Login como admin. 2) Acceder CRM. 3) Automation 4) Config | F39: Al entrar en config carga infinitamente | G39: Debería cargar la configuracion | H39: Captura de pantalla 2026-05-18 124147.png | I39: Bloqueante | J39: JUN06, JZO,Randú
A40: =IF(C39="","","BUG-"&TEXT(ROW()-1,"000")) -> BUG-039 | B40: 46160 | C40: 46179 | D40: Otra | E40: 1) Login como admin. 2) Acceder a crm 3) acceder a llistas . 4)Acceder a listas 5) acción -<enviar correo . | F40: al enviar un correo a un usuario, no se envia, y muestra un mensaje de error raro | G40: Debería poder envia un correo al usuario correctamente | H40: https://drive.google.com/file/d/1p18i2Ort671rvwqx3muUvPLLAhU__ISl/view?usp=drive_link | I40: Menor
A41: =IF(C40="","","BUG-"&TEXT(ROW()-1,"000")) -> BUG-040 | B41: 46160 | C41: RGP | D41: Otra | E41: 1) Login como admin. 2) Acceder CRM. 3) Automation 4) Config 5) Add new | F41: Al entrar en automation/config y add new, se queda cargando infinitamente | G41: Debería dejar cargar algo | H41: Captura de pantalla 2026-05-18 124443.png | I41: Bloqueante | J41: JUN06,
A42: =IF(C41="","","BUG-"&TEXT(ROW()-1,"000")) -> BUG-041 | B42: 46160 | C42: RGP | D42: Otra | E42: 1) Login como admin. 2) Acceder CRM. 3) Automation 4) Scheduled Automation Tasks | F42: Al entrar en Automation/Scheduled Automation Tasks no deja borrar el Lead. | G42: Falta el botón de actions para poder borrar desde ahí. | H42: Captura de pantalla 2026-05-18 125948.png | I42: Grave
A43: =IF(C42="","","BUG-"&TEXT(ROW()-1,"000")) -> BUG-042 | B43: 46160 | C43: JZO | D43: Otra | E43: 1) Login como admin. 2) Acceder CRM 3) Acceder a Label 4) Seleccionar Label 5) Seleccionar Actions y delete | F43: Da un error al intentar eliminar un Laber | G43: Poder eliminar el Label correspondiente | H43: https://drive.google.com/file/d/15QtaHzDagVmDDB4gS97W7KLAD0g-09rt/view?usp=drive_link | I43: Menor
A44: =IF(C43="","","BUG-"&TEXT(ROW()-1,"000")) -> BUG-043 | B44: 46160 | C44: 46179 | D44: Otra | E44: 1) Login como admin. 2) Acceder CRM. 3) Acceder a Preguntas Frecuentes. 4) Buscar pregunta. | F44: No encuentra la pregunta ya creada. | G44: Encontrar la pregunta. | H44: https://drive.google.com/file/d/1LpMbdpOOXKmIYBVzeQckboKuefcjLPKt/view?usp=drive_link | I44: Menor
A45: =IF(C44="","","BUG-"&TEXT(ROW()-1,"000")) -> BUG-044 | B45: 46160 | C45: RGP | D45: Otra | E45: 1) Login como admin. 2) Cambiar el idiomar. | F45: Solo se traducen algunos campos | G45: Deberían de traducirse automáticamente todos los campos y no sólo algunos | H45: Captura de pantalla 2026-05-18 130603.png | I45: Menor
A46: =IF(C45="","","BUG-"&TEXT(ROW()-1,"000")) -> BUG-045 | B46: 46160 | C46: 46182 | D46: Otra | E46: 1).Login como admin 2).Dashboard 3).clincs | F46: El boton de localizar mediante el codigo la region, pais y ciudad no funciona, no localiza, no realiza ninguina accion | G46: Que al introducir el codigo postal correcto, se rellenara solo los campos | I46: Menor
A47: =IF(C46="","","BUG-"&TEXT(ROW()-1,"000")) -> BUG-046 | B47: 46160 | C47: JZO | D47: CRM | E47: 1) Login como admin. 2) Acceder a Leads 3) Seleccionar Lead. 4)Eliminar Lead | F47: Supuestamente los task del Lead estan eliminados y aun asi aparacen a la hora de eliminar el lead como si existiesen | G47: Que no aparezcan los task eliminados y deje elimar el lead. | H47: https://drive.google.com/file/d/1-otLb6MrDGGZb8qPL_D-Ya1jELfoH889/view?usp=drive_link | I47: Menor
A48: =IF(C47="","","BUG-"&TEXT(ROW()-1,"000")) -> BUG-047 | B48: 46160 | C48: RGP | D48: CRM | E48: 1) Login como admin. 2) CRM 3) Notas | F48: Está mal escrito el mensaje. | G48: Debería poner "fetched" | H48: Captura de pantalla 2026-05-18 131207.png | I48: Menor
A49: =IF(C48="","","BUG-"&TEXT(ROW()-1,"000")) -> BUG-048 | B49: 46160 | C49: 46182 | D49: Otra | E49: 1).Login como Admin. 2) Dashboard 3).Doctor | F49: En el apartado email apartir del @ puedes poner cualquiercosa.com es decir uwe@ajjajajja.com y te lo valida | G49: Deberia mandarte una alerta que te diga que el correo introducido no es valido o no existe esa extension | I49: Menor
A50: =IF(C49="","","BUG-"&TEXT(ROW()-1,"000")) -> BUG-049 | B50: 46160 | C50: RGP | D50: Otra | E50: 1).Login como Admin. 2) Cualquier ventana | F50: Al presionar el boton Saludti, te manda al mismo lado donde ya estás. | G50: Debería de mandar al home o a algún otro sitio, no que te mande donde ya estás. | H50: 1.png | I50: Menor
A51: BUG-050 | B51: 46160 | C51: 46179 | D51: Otra | E51: 1) Login como admin. 2) Acceder CRM. 3) Acceder a Preguntas Frecuentes. 4) Generate FAQs from Document | F51: Al subir un FAQ generado por un documento no genera la pregunta, dando error no recibiendo datos del documento enviado. | G51: Debería generar la pregunta y actualizar la lista de preguntas. | H51: https://drive.google.com/file/d/1fCIcEbl-McMjgPm7lgWkH9GfZc1VfK3U/view?usp=drive_link | I51: Menor
A52: =IF(C51="","","BUG-"&TEXT(ROW()-1,"000")) -> BUG-051 | B52: 46160 | C52: 46184 | D52: Crear doctor | E52: 1) Login como admin. 2) Clinical Service- Doctor. 3) Pulsar "+ Agregar Nuevo". | F52: Al momento de crear un doctor en "Professional Contact Information" en el input de correo admite mayuscula en ...@GMAIL.COM o @GMAIL.COMA lo cual es inexistente | G52: Deberia mandarte una alerta que te diga que el correo introducido no es valido o no existe esa extension | H52: https://drive.google.com/file/d/1Nu1-XfSXOqVSpapNTzpvwfKjDmu-fI-_/view?usp=drive_link | I52: Grave
A53: =IF(C52="","","BUG-"&TEXT(ROW()-1,"000")) -> BUG-052 | B53: 46160 | C53: 46184 | D53: Crear doctor | E53: 1) Login como admin. 2) Clinical Service- Doctor. 3) Pulsar "+ Agregar Nuevo". | F53: Al momento de crear un doctor en "Professional Contact Information" en el input de "phone number " no te restringe la cantidad de numeros lo cual puedes crear un telefono con cantidades inexistentes | G53: deberia enviar un aviso de que el numero de telefono si es muy extenso no existe | H53: https://drive.google.com/file/d/1Nu1-XfSXOqVSpapNTzpvwfKjDmu-fI-_/view?usp=drive_link | I53: Grave
A54: =IF(C53="","","BUG-"&TEXT(ROW()-1,"000")) -> BUG-053 | B54: 46160 | C54: 46184 | D54: Crear doctor | E54: 1) Login como admin. 2) Clinical Service- paciente . 3) Pulsar "+ Agregar Nuevo". | F54: al momento de crear "Professional Contact Information" en el input de DNI permite la creacion del pacinete ya sea que el paciente tenga un nie de "#~#€~€¬~" | G54: deberia avisar que el dni que coloca no existe | H54: https://drive.google.com/file/d/1b5ULM4Bk6MLkYkVLCYEudFAIQud7rxA5/view?usp=drive_link | I54: Menor
A55: =IF(C54="","","BUG-"&TEXT(ROW()-1,"000")) -> BUG-054 | B55: 46160 | C55: 46185 | D55: Crear paciente | E55: 1) Login como admin. 2) Clinical Service- paciente . 3) Pulsar "+ Agregar Nuevo". | F55: Date of Birth y Gender obligatorios sin asterisco * que indique que esos campos lo son | G55: Deberiaria indicar con asterisriscos que esos campos son obligatorio | H55: https://drive.google.com/file/d/1uBfqdVQlTu1lgYcBTQXLKkEGry8J9e0E/view?usp=sharing
A56: =IF(C55="","","BUG-"&TEXT(ROW()-1,"000")) -> BUG-055 | B56: 46160 | C56: 46185 | D56: Crear paciente | E56: 1) Login como admin. 2) Clinical Service- paciente . 3) Pulsar "+ Agregar Nuevo". | F56: Blood Group/Allergies/Habits salen con borde rojo sin ser obligatorios | G56: Al no ser obligarios no deberian aparecer con bordes rojos, eso crea confusion | H56: https://drive.google.com/file/d/1qNirf53LtL1wVWhiQDFfU7NvQNfBtOsf/view?usp=sharing
A57: =IF(C56="","","BUG-"&TEXT(ROW()-1,"000")) -> BUG-056 | B57: 46160 | C57: 46185 | D57: Crear paciente | E57: 1) Login como admin. 2) Clinical Service- paciente . 3) Editar paciente | F57: Los campos obligatorios como correo o telefono no se validan otravez cuando se edita la informacion de un paciente | G57: deberia validar el formulario otra vez al actualizar la informacion de un paciente para evitar errores | H57: https://drive.google.com/file/d/1UhVYJagHP00v6TrT11lQO_NnMdpUBgNn/view?usp=sharing
A58: =IF(C57="","","BUG-"&TEXT(ROW()-1,"000")) -> BUG-057 | B58: 46160 | C58: 46185 | D58: Crear paciente | E58: 1) Login como admin. 2) Clinical Service- paciente . 3) Pulsar "+ Agregar Nuevo". | F58: el campo DNI no valida el formato | G58: Para asegurar que no se introduzca un identificador no valido debreia verfificar el formato | H58: https://drive.google.com/file/d/1UhVYJagHP00v6TrT11lQO_NnMdpUBgNn/view?usp=sharing | J58: Randú
A59: =IF(C58="","","BUG-"&TEXT(ROW()-1,"000")) -> BUG-058 | B59: 46160 | C59: 46184 | D59: Citas (admin) | E59: 1) Login como admin. 2) Clinical Service- CITAS. 3) Pulsar "+CITA RAPIDA". | F59: he notado que se puede citar a 2 pacientes en el mismo horario y con el mismo doctor | G59: deberia de poder mostrar solo los horarios disponibles | H59: https://drive.google.com/file/d/1BuK4bmOmS3gLhNImRfBzCUF9A8H4No0_/view?usp=drive_link | I59: Grave
A60: =IF(C59="","","BUG-"&TEXT(ROW()-1,"000")) -> BUG-059 | B60: 46160 | C60: 46184 | D60: Citas (admin) | E60: 1)login como admin 2)Patient Management 3)Appointments 4)add new | F60: son 4 pasos que se requiere para poder realizar un appointements/cita lo cual solo puedes llegar hasta el 3 paso porque basicamente no te deja ver los horarios disponibles del doctor y tampoco te deja pillar un horario que quieres por ese motivo no te deja saltar al siguiente paso | G60: deberia de salir el espacio disponible y poder selecionar para saltar al siguiente paso-4 | H60: https://drive.google.com/file/d/1RxbWwUyTm0T29-nxcFa6ImeDtrV_UtR_/view?usp=drive_link | I60: Menor
A61: =IF(C60="","","BUG-"&TEXT(ROW()-1,"000")) -> BUG-060 | B61: 46161 | C61: DMT | D61: Otra | E61: 1) Login como admin. 2) Acceder a clínicas. 3) Crear clínica. | F61: Los asteriscos no aparecen en rojo a diferencia de el resto de páginas, creando una incosistencia visual. | G61: Que los asteriscos aparezcan de color rojo. | H61: Screenshot_20260519_084042.png | I61: Menor
A62: =IF(C61="","","BUG-"&TEXT(ROW()-1,"000")) -> BUG-061 | B62: 46161 | C62: DMT | D62: Otra | E62: 1) Login como admin. 2) Acceder a clínicas. 3) Crear clínica. | F62: Los campos de imágenes y vídeos permiten borrar el contenido aunque aún no se haya subido nada. | G62: Que no aparezca el contenido vacío ni los botones de borrar. | H62: Screenshot_20260519_091229.png | I62: Menor
A63: =IF(C62="","","BUG-"&TEXT(ROW()-1,"000")) -> BUG-062 | B63: 46161 | C63: DMT | D63: Otra | E63: 1) Login como admin. 2) Acceder a clínicas. 3) Crear clínica. | F63: El botón de localizar a través de código ZIP no funciona. | G63: Localizar la ubicación a través del código ZIP | H63: Screenshot_20260519_092316.png | I63: Menor
A64: =IF(C63="","","BUG-"&TEXT(ROW()-1,"000")) -> BUG-063 | B64: 46161 | C64: DMT | D64: Otra | E64: 1) Login como admin. 2) Acceder a clínicas. 3) Crear clínica. | F64: El campo CIF permite introducir cualquier dato. | G64: Al igual que el campo de email solo permite emails válidos, el campo de CIF solo debería permitir una cadena de una letra seguida de 8 caracteres, ya que todos los números CIF cumplen con esta sucesión. | H64: Screenshot_20260519_093518.png | I64: Menor
A65: =IF(C64="","","BUG-"&TEXT(ROW()-1,"000")) -> BUG-064 | B65: 46161 | C65: DMT | D65: Otra | E65: 1) Login como admin. 2) Acceder a clínicas. 3) Crear clínica. | F65: Los campos de Correo y Dirección son obligatorios, pero no aparecen marcados con el asterisco de obligatorio. | G65: Que dichos campos aparezcan indicados como obligatorios. | H65: Screenshot_20260519_093853.png | I65: Menor
A66: =IF(C65="","","BUG-"&TEXT(ROW()-1,"000")) -> BUG-065 | B66: 46161 | C66: DMT | D66: Otra | E66: 1) Login como admin. 2) Acceder a clínicas. 3) Ver detalles de clínica | F66: El apartado de ver detalles redirige a editar detalles en su lugar, lo cual a demás no permite visualizar ni vídeos ni imágenes adjuntas. | G66: Redirigir al apartado de ver detalles. | H66: Screenshot_20260519_094621.png | I66: Grave
A67: =IF(C66="","","BUG-"&TEXT(ROW()-1,"000")) -> BUG-066 | B67: 46161 | C67: JZO | D67: Otra | E67: 1) Login como admin. 2) Acceder a clínicas. 3) Acceder a Pivot View. 4) Acceder a type | F67: Al seleccionar el apartado de type redirige a una pantalla en blanco | G67: Redirir a una pantalla funcional | H67: https://drive.google.com/file/d/1XHmy1qlg9SMry-i1blEw2XZ7jPIvfC1G/view?usp=drive_link | I67: Bloqueante
A68: =IF(C67="","","BUG-"&TEXT(ROW()-1,"000")) -> BUG-067 | B68: 46161 | C68: DMT | D68: CRM | E68: 1) Login como admin. 2) Acceder al apartado de contactos del CRM. 3) Mandar solicitud de contacto. 4) Abrir panel de notificaciones. 5) Cancelar solicitud. | F68: El botón de cancelar solicitud no funciona. | G68: Al presionar el botón se debería cancelar la solicitud | H68: Screenshot_20260519_105111.png | I68: Grave
A69: =IF(C68="","","BUG-"&TEXT(ROW()-1,"000")) -> BUG-068 | B69: 46161 | C69: RGP | D69: Otra | E69: 1) Login como admin 2) Dashboard | F69: El botón "My Schedules" no hace nada | G69: Debería llevarte a "My Schedules" | H69: Captura de pantalla 2026-05-19 111242.png | I69: Menor
A70: =IF(C69="","","BUG-"&TEXT(ROW()-1,"000")) -> BUG-069 | B70: 46161 | C70: RGP | D70: Otra | E70: 1) Login como admin. 2) Clinical Service. 3) Doctor. 4) Add new 5) Upload banner or presentation video | F70: No deja subir ni vídeos ni fotos de banner | G70: Debería de dejar cargar vídeos y fotos. | H70: Captura de pantalla 2026-05-19 112704.png | I70: Grave
A71: =IF(C70="","","BUG-"&TEXT(ROW()-1,"000")) -> BUG-070 | B71: 46161 | C71: Randú | D71: Servicios | E71: 1) Login como admin. 2) Clinical Service. 3) Orders. 4) Click +add new. | F71: redirige a un banner que dice cargando datos, pero la carga nunca se completa. | G71: Un formulario para crear la order. | H71: https://drive.google.com/file/d/1cV8mAMtKaYfjeCIXb0OOytEHxC1kz3ZQ/view?usp=drive_link | I71: Bloqueante
A72: =IF(C71="","","BUG-"&TEXT(ROW()-1,"000")) -> BUG-071
A73: =IF(C72="","","BUG-"&TEXT(ROW()-1,"000"))
A74: =IF(C73="","","BUG-"&TEXT(ROW()-1,"000"))
A75: =IF(C74="","","BUG-"&TEXT(ROW()-1,"000"))
A76: =IF(C75="","","BUG-"&TEXT(ROW()-1,"000"))
A77: =IF(C76="","","BUG-"&TEXT(ROW()-1,"000"))
A78: =IF(C77="","","BUG-"&TEXT(ROW()-1,"000"))
A79: =IF(C78="","","BUG-"&TEXT(ROW()-1,"000"))
A80: =IF(C79="","","BUG-"&TEXT(ROW()-1,"000"))
A81: =IF(C80="","","BUG-"&TEXT(ROW()-1,"000"))
A82: =IF(C81="","","BUG-"&TEXT(ROW()-1,"000"))
A83: =IF(C82="","","BUG-"&TEXT(ROW()-1,"000"))
... A99: =IF(C98="","","BUG-"&TEXT(ROW()-1,"000"))
A100: BUG-099 | B100: 2026-05-19 | C100: RDC | D100: CRM | E100: 1) Login como admin. 2) Acceder al apartado de contactos del CRM. 3) Mandar solicitud de contacto. 4) Abrir panel de notificaciones. 5) Cancelar solicitud. | F100: El botón de cancelar solicitud no funciona. | G100: Al presionar el botón se debería cancelar la solicitud. | H100: https://drive.google.com/file/d/1XHmy1qlg9SMry-i1blEw2XZ7jPIvfC1G/view?usp=drive_link | I100: Grave
A101: BUG-100 | B101: 2026-05-19 | C101: RDC | D101: Otra | E101: 1) Login como admin 2) Dashboard | F101: El botón "My Schedules" no hace nada. | G101: Debería llevarte a "My Schedules". | H101: Screenshot_20260519_105111.png | I101: Grave
A102: BUG-101 | B102: 2026-05-19 | C102: RDC | D102: Crear doctor | E102: 1) Login como admin. 2) Clinical Service. 3) Doctor. 4) Add new 5) Upload banner or presentation video | F102: No deja subir ni vídeos ni fotos de banner. | G102: Debería de dejar cargar vídeos y fotos. | H102: Captura de pantalla 2026-05-19 111242.png | I102: Bloqueante
A103: BUG-102 | B103: 2026-05-19 | C103: RDC | D103: Servicios | E103: 1) Login como admin. 2) Clinical Service. 3) Orders. 4) Click +add new. | F103: redirige a un banner que dice cargando datos, pero la carga nunca se completa. | G103: Un formulario para crear la order. | H103: https://drive.google.com/file/d/1cV8mAMtKaYfjeCIXb0OOytEHxC1kz3ZQ/view?usp=drive_link | I103: Bloqueante
A104: BUG-103 | B104: 2026-05-19 | C104: RDC | D104: CRM | E104: 1) Login como admin. 2) Acceder al apartado de contactos del CRM. 3) Elegir contacto. | F104: Al seleccionar el apartado de type redirige a una pantalla en blanco. | G104: Cargar la interfaz para añadir la orden y poder añadir una nueva sin ningún error. | I104: Grave
A105: BUG-104 | B105: 2026-05-18 | C105: JUN12 | D105: Crear paciente | E105: 1) Login como admin. 2) Ir a Clinical Management > Patients. 3) Crear paciente "Rodrigo Donoso" con DNI: RDC012345, email: rdc.1985@gmail.com, teléfono: 604970466. 4) Guardar correctamente. 5) Ir a New Patient > buscar por teléfono 604970466. 6) Ignorar la sugerencia y rellenar el formulario con nombre diferente "Patricia", DNI, email, teléfono. 7) Pulsar Save. | F105: El sistema permite crear un segundo paciente (ID 3639 "Patricia") con exactamente los mismos datos que uno existente (ID 2472 "Rodrigo Donoso"): mismo DNI RDC012345, mismo email rdc.1985@gmail.com y mismo teléfono 604970466. Solo cambia el nombre. No aparece ningún aviso de duplicado. | G105: El sistema debería detectar que ya existe un paciente con el mismo DNI (y/o email o teléfono) y mostrar un aviso del tipo "Ya existe un paciente con este DNI". No debería permitir guardar el duplicado. | H105: Captura_2026-05-18_10_33.png, Captura_2026-05-18_10_39.png | I105: Grave
A106: BUG-105 | B106: 2026-05-18 | C106: JUN12 | D106: Crear paciente | E106: 1) Login como admin. 2) Crear un paciente nuevo asignado a la clínica MEPRYSA REHABILITACION. 3) Guardar el paciente. 4) Abrir el paciente creado y desplazarse hasta la sección "Patient Consent Documents". | F106: La sección "Patient Consent Documents" muestra dos entradas duplicadas para la misma clínica "MEPRYSA REHABILITACION", ambas con fecha 18/5/2026 y estado "No consent uploaded". Solo se asignó la clínica una vez durante la creación del paciente. | G106: Debería aparecer una única entrada por clínica en la sección Patient Consent Documents. | H106: Captura_de_pantalla_2026-05-18_a_las_10_39_40.png | I106: Menor
A107: BUG-106 | B107: 2026-05-18 | C107: JUN12 | D107: Crear paciente | E107: 1) Login como admin. 2) Crear paciente "Helena" con DNI: RDC012345 (igual que Rodrigo Donoso), email: rdc.1985@gmail.com, teléfono: 604970466. 3) Guardar. 4) Buscar "HELENA" en lista. -> No aparece. PRUEBA 2: 1) Crear paciente "Helena" con DNI diferente: HEL012345, mismo email y teléfono. 2) El sistema muestra "You have added the patient successfully." 3) Buscar "Helena" en lista de pacientes. -> Tampoco aparece. | F107: Helena no aparece en ninguna búsqueda: ni por nombre, ni por email, ni por teléfono. El sistema confirmó "You have added the patient successfully" pero el registro no es recuperable por ningún campo. | G107: Helena debería aparecer en los resultados al buscar por nombre, email o teléfono. El registro se confirmó como creado pero es completamente irrecuperable desde la interfaz. | H107: Captura_2026-05-18_10_52_54.png, Captura_2026-05-18_10_53_52.png, Captura_2026-05-18_10_54_13.png, Captura_2026-05-18_10_55_47.png, Captura_2026-05-18_10_55_59.png | I107: Bloqueante
A108: BUG-107 | B108: 2026-05-18 | C108: JUN12 | D108: Crear paciente | E108: 1) Login como admin. 2) Ir a Clinical Management > Patients. 3) Buscar por teléfono "604970466". | F108: La búsqueda devuelve 3 pacientes distintos con el mismo número de teléfono: Suchandra Banerjee (ID-2473), Rodrigo Donoso (ID-2472) y Patricia (ID-3639). | G108: El sistema debería impedir asignar el mismo número de teléfono a más de un paciente, o al menos mostrar un aviso de posible duplicado. | H108: Captura_2026-05-18_10_55_59.png | I108: Grave
A109: BUG-108 | B109: 2026-05-18 | C109: JUN12 | D109: Crear paciente | E109: 1) Login como admin. 2) Ir a Clinical Management > Patients > Add New. 3) Rellenar nombre, DNI: RDC012345, email: rdc.1985@gmail.com, teléfono: 604970466. 4) En el campo "Date of Birth" introducir una fecha con año imposible: 30/04/719251. 5) Observar el campo "Age" sin pulsar nada. 6) Pulsar Save. | F109: El campo "Age" calcula automáticamente -273734 años. El sistema no muestra ningún aviso de error ni impide continuar. Al pulsar Save el paciente se guarda con la fecha imposible. | G109: El campo Date of Birth debería validar que el año esté en un rango razonable (ej. 1900-año actual). Si el año es imposible, debería mostrar un error e impedir guardar. | H109: Captura_2026-05-18_11_13_09.png, Captura_2026-05-18_11_13_39.png | I109: Grave
A110: BUG-109 | B110: 2026-05-18 | C110: JUN12 | D110: Crear paciente | E110: 1) Login como admin. 2) Ir a Clinical Management > Patients > Add New. 3) En el campo "Date of Birth" introducir 31/02/1951 (fecha inexistente). 4) Hacer clic fuera del campo o pulsar Save. | F110: El sistema muestra el mensaje de error "Date of Birth is required" en rojo bajo el campo, como si el campo estuviera vacío, a pesar de tener un valor. | G110: El sistema debería mostrar un mensaje específico indicando que la fecha introducida es inválida (ej. "Fecha no válida"), no que es requerida. | H110: Captura_2026-05-18_11_18_11.png | I110: Menor
A111: BUG-110 | B111: 2026-05-18 | C111: JUN12 | D111: Crear paciente | E111: 1) Login como admin. 2) Crear nuevo paciente: nombre "Eduardo", apellido "Donoso", DNI: RDC012345, email: rdc.1985@gmail.com, teléfono: 604970466. 3) Pulsar Save. 4) Buscar "Eduardo" en la lista. 5) Buscar por email "rdc.1985". | F111: Tras confirmarse la creación, el nuevo Eduardo Donoso no figura en la lista. Al buscar por email "rdc.1985" aparecen solo Rodrigo y Patricia. El nuevo paciente es irrecuperable. | G111: El paciente recién creado debe aparecer inmediatamente en la lista al buscar por nombre o email. | H111: Captura_2026-05-18_11_14_56.png, Captura_2026-05-18_11_17_14.png, Captura_2026-05-18_11_18_53.png, Captura_2026-05-18_11_19_46.png, Captura_2026-05-18_11_20_21.png | I111: Bloqueante
A112: =IF(C111="","","BUG-"&TEXT(ROW()-1,"000")) -> BUG-111 | B112: 2026-05-18 | C112: JUN12 | D112: Crear paciente | E112: PRUEBA DE CONTROL con datos 100% únicos: 1) Login como admin. 2) Ir a Patients > Add New. 3) Rellenar: nombre "Eduardo", apellido "Donoso", DNI: EDU012345, email: rod.donosocaceres@gmail.com, teléfono: 604970478 (todos únicos). 4) Pulsar Save. 5) Buscar por teléfono 604970478. | F112: El sistema muestra "You have update the patient successfully." (dice UPDATE aunque es nuevo). El paciente Eduardo Donoso (ID-3644) sí aparece en la búsqueda por teléfono. Esto confirma que cuando email o teléfono coinciden con un paciente existente, el sistema hace un UPDATE silencioso sobreescribiendo el registro existente sin avisar. | G112: El sistema nunca debe hacer un UPDATE silencioso al usar "Add New". Debe mostrar un aviso explícito si el email o teléfono ya están asignados a otro paciente. | H112: Captura_2026-05-18_11_29_54.png, Captura_2026-05-18_11_30_09.png, Captura_2026-05-18_11_30_48.png | I112: Bloqueante
A113: BUG-112 | B113: 2026-05-18 | C113: JUN12 | D113: Crear paciente | E113: 1) Login como admin. 2) Ir a Patients > Add New. 3) En DNI introducir "HEL" (solo letras). 4) Rellenar resto de campos y pulsar Save. | F113: El sistema acepta "HEL" como DNI válido y guarda el paciente sin ningún aviso de error o formato inválido. | G113: El campo DNI debería validar el formato (ej. 8 dígitos y 1 letra para España) y mostrar un error si es inválido. | H113: Captura_2026-05-18_11_33_06.png, Captura_2026-05-18_11_33_14.png | I113: Grave
A114: BUG-113 | B114: 2026-05-18 | C114: JUN12 | D114: Crear paciente | E114: 1) Login como admin. 2) Ir a Patients > Add New. 3) Introducir en Name: "LI9" (con números). 4) Introducir en Surname: "675" (solo números). 5) Pulsar Save. | F114: El sistema acepta "LI9" como nombre y "675" como apellido sin avisos. El paciente se guarda (ID-3646) y aparece con esos datos. | G114: Los campos de Name y Surname deberían validar que solo contengan letras y caracteres alfabéticos. | H114: Captura_2026-05-18_11_39_56.png, Captura_2026-05-18_11_41_33.png | I114: Grave
A115: BUG-114 | B115: 2026-05-18 | C115: JUN12 | D115: Crear paciente | E115: 1) Login como admin. 2) Crear cualquier paciente nuevo con datos únicos. 3) Pulsar Save. 4) Observar la pantalla inmediatamente después de guardar. | F115: Al guardar aparecen simultáneamente dos mensajes de confirmación: un modal central que dice "Congratulations – You have update the patient successfully" y un toast verde que dice "Patient saved successfully!". | G115: Debería mostrarse un único mensaje de confirmación, coherente (ej. "Patient added successfully" si es nuevo). | H115: Captura_2026-05-18_11_40_13.png | I115: Menor
...

Sheet Propuestas de mejora
A1: Las propuestas de mejora NO son bugs. Aquí va lo que "se podría hacer mejor". El PM las revisa después del piloto, no en sprint.
A2: ID | B2: Fecha | C2: Tester | D2: Área | E2: Propuesta | F2: Por qué la propones | G2: Prioridad sugerida | H2: Estado | I2: Notas del PM
A3: =IF(C2="","","MEJ-"&TEXT(ROW()-1,"000")) -> MEJ-002 | B3: 46156 | C3: 46175 | D3: CRM | E3: Indicar los campos obligatorios en las ventanas emergentes de creación o edición de datos, como la creación rápida de leads. | F3: Los usuarios deben de ser capaces de visualizar al momento que campos deben rellenar obligatoriamente | G3: Baja
A4: =IF(C3="","","MEJ-"&TEXT(ROW()-1,"000")) -> MEJ-003 | B4: 46156 | C4: 46176 | D4: CRM | E4: Eliminar el botón lateral izquierdo de acciones en la lista de leads, reemplazarlo con un botón de editar lead y añadir enlace en el identificador del lead para ver sus detalles | F4: El botón de acciones de lead es poco intuitivo y tiene el mismo nombre que otro elemento de la página, lo cual puede llevar a confusión. A demás, todos los apartados de vista se encuentran dentro de View Details, por lo que es inncesario crear varios botónes. | G4: Media
A5: =IF(C4="","","MEJ-"&TEXT(ROW()-1,"000")) -> MEJ-004 | B5: 46160 | C5: 46181 | D5: Calendario/Agenda | E5: Poder tener la función de agendar tareas en el calendario | F5: Para poder llevar al dia y tener cierto control y organización en las tareas a realizar. | G5: Baja
A6: =IF(C5="","","MEJ-"&TEXT(ROW()-1,"000")) -> MEJ-005 | B6: 46160 | C6: 46183 | D6: CRM | E6: Al crear un Schedule Automation, se podría crear dos opciones al presionar Save as template, que sea privado y público, y que no se dé por hecho que se sabe que se crea como privado, para evitar confusiones y queda más limpio. | F6: Al crear una automatización se podría confundir una persona si no sabe que salen privadas, por eso mejor crear dos opciones. | G6: Baja
A7: =IF(C6="","","MEJ-"&TEXT(ROW()-1,"000")) -> MEJ-006 | B7: 46160 | C7: 46177 | D7: CRM | E7: En la sección de media Library, en vez de poder permitir, que dos archivos tengan el mismo nombre con la misma extensión, se añada un identificador, como por ejemplo; archivo, archivo(1) | F7: Los nombres del archivo de un usuario, si tienen el mismo nombre, y con la misma extensión del archivo, podría darse el caso de que lleve a una confusión, a la hora de adjntar un archivo, de compartirlo o inciar una automatización, puede ocurrir con el archivo equivocado | G7: Baja
A8: =IF(C7="","","MEJ-"&TEXT(ROW()-1,"000")) -> MEJ-007 | B8: 46160 | C8: 46183 | D8: Otra | E8: En la sección Automation, Schedule Child Tasks podría ser una subsección de Schedule Tasks o que no salga como otra pestaña cuando está relacionado directamente, para que quede más limpio. | F8: Creo que quedaría más limpio dejaría menos margen a confusiones. | G8: Baja
A9: =IF(C8="","","MEJ-"&TEXT(ROW()-1,"000")) -> MEJ-008 | B9: 46160 | C9: 46175 | D9: Otra | E9: Crear un botón de creación rápida para las clínicas | F9: Al igual que se puede realizar una creación rápida de leads, las clínicas también tienen pocos cambios obligatorios, por lo que esto podría acelerar el flujo inicial de creación de clínicas y/o productos/clientes para ellas | G9: Media
A10: =IF(C9="","","MEJ-"&TEXT(ROW()-1,"000")) -> MEJ-009 | C10: RDC | D10: Crear paciente | E10: Añadir campo "Contacto del tutor/responsable legal" para pacientes menores de edad. Cuando el paciente tiene menos de 18 años (calculado por fecha de nacimiento), mostrar automáticamente campos opcionales: nombre del tutor, teléfono del tutor, email del tutor. Estos datos quedarían vinculados como contacto de emergencia/tutor, separados del email/teléfono del propio paciente. | F10: Actualmente para pacientes menores de edad no hay forma de registrar el contacto del padre/tutor de forma estructurada. Si se usa el email/teléfono del padre en los campos del paciente, el sistema los trata como datos del menor y además puede sobreescribir el registro del padre (BUG-036). Un paciente de 4 años no tiene email propio — el sistema debería contemplar este caso. | G10: Alta
A11: =IF(C10="","","MEJ-"&TEXT(ROW()-1,"000")) -> MEJ-010 | C11: RDC | D11: Crear doctor | E11: Añadir opción 'Medicina General' (u equivalente) en el selector de Medical Specialities, y/o hacer el campo obligatorio con un mensaje claro si se intenta guardar sin especialidad. Si el sistema permite médicos sin especialidad, mostrar un aviso tipo 'Este doctor no tendrá especialidad asignada y podría no aparecer en búsquedas de citas filtradas por especialidad'. | F11: Un doctor sin especialidad queda potencialmente inutilizable en el flujo de asignación de citas si ese flujo filtra por especialidad. Además, 'Medicina General' es la especialidad más común en atención primaria y debería estar disponible como opción. | G11: Alta
A12: =IF(C11="","","MEJ-"&TEXT(ROW()-1,"000")) -> MEJ-011 | C12: RDC | D12: Crear doctor | E12: Ampliar los campos obligatorios del formulario de alta de doctor para evitar fichas vacías en producción. Campos sugeridos como obligatorios: DNI/NIF (ver BUG-044), Medical Speciality (al menos una), Position/Title. Campos sugeridos como recomendados con aviso: Years of Experience, Qualifications, Medical Council. El progreso del formulario ya muestra '78% Complete' al rellenar solo los mínimos — ese indicador debería llegar al 100% solo cuando los datos clínicamente relevantes estén completos. | F12: Con los mínimos actuales (nombre + número de colegiado + email/teléfono) el doctor queda creado con Doctor ID placeholder, sin especialidad, sin horario y sin qualificaciones. Una ficha tan vacía no es útil para el flujo clínico real (asignación de citas, facturación, prescripciones). | G12: Alta
A13: =IF(C12="","","MEJ-"&TEXT(ROW()-1,"000")) -> MEJ-012 | C13: RDC | D13: Crear cita / Quick Appointment | E13: Añadir texto de ayuda o tooltip en el campo 'Notes for Doctor' del Step 3 que explique: (1) Dónde ve el médico la nota (agenda, ficha del paciente, notificación). (2) Cuándo la recibe. (3) Si se puede editar después de confirmar la cita. Adicionalmente, mostrar en la ficha de la cita confirmada las notas introducidas, para que el admin pueda verificar que llegaron correctamente. | F13: El campo es obligatorio pero su propósito y destino son opacos. El personal administrativo no puede saber si su mensaje llega al médico ni cómo. En producción esto genera desconfianza en el sistema y workarounds (llamadas telefónicas, WhatsApp). | G13: Media
A16: =IF(C15="","","MEJ-"&TEXT(ROW()-1,"000"))
A17: =IF(C16="","","MEJ-"&TEXT(ROW()-1,"000"))
A18: =IF(C17="","","MEJ-"&TEXT(ROW()-1,"000"))
A19: =IF(C18="","","MEJ-"&TEXT(ROW()-1,"000"))
A20: =IF(C19="","","MEJ-"&TEXT(ROW()-1,"000"))
A21: =IF(C20="","","MEJ-"&TEXT(ROW()-1,"000"))
A22: =IF(C21="","","MEJ-"&TEXT(ROW()-1,"000"))
A23: =IF(C22="","","MEJ-"&TEXT(ROW()-1,"000"))
A24: =IF(C23="","","MEJ-"&TEXT(ROW()-1,"000"))
A25: =IF(C24="","","MEJ-"&TEXT(ROW()-1,"000"))
A26: =IF(C25="","","MEJ-"&TEXT(ROW()-1,"000"))
A27: =IF(C26="","","MEJ-"&TEXT(ROW()-1,"000"))
... A302: =IF(C301="","","MEJ-"&TEXT(ROW()-1,"000"))

Sheet Plan de testing
B1: Plan de testing por semana
B4: Semana | C4: Áreas a probar | D4: Foco / instrucciones
B5: Semana 1 | C5: Crear paciente • Crear doctor • Calendario/Agenda • Citas (admin) | D5: Romper el alta de pacientes y doctores. Probar datos inválidos, vacíos, duplicados, caracteres raros. Crear citas en huecos ocupados, en huecos libres, en pasado, en futuro lejano.Investigar el proceso entero de creación y explorar las vías que se permiten.
B6: Semana 2 | C6: Sales orders / Facturación • Retell • CRM | D6: Foco principal: facturación end-to-end. Casos: paciente particular, paciente con mutua, varios servicios añadidos en consulta, anulación de factura, división de pagos. Atacar especialmente la duplicación de importes. Retell: revisar que la grabación del webhook es coherente con la llamada real.
B7: Semana 3 | C7: Historia clínica + IA • Servicios • XLS uploads/Mapping | D7: IA: probar dictados largos, cortos, con interrupciones, con varios hablantes, en silencio. Verificar que la historia clínica generada es coherente. Servicios y XLS: subir XLS con encabezados raros, datos faltantes, formatos numéricos distintos, símbolos.
B8: Semana 4 | C8: Cancel automation • Web pública • Retesteo de bugs verificados | D8: Cancel automation: ejecutar sobre lotes de varias citas a la vez, verificar que cada paciente recibe solo una notificación, no varias. Web: revisar que botones llevan a donde deben, formulario de cita funciona. Resto del tiempo: reverificar bugs marcados como Arreglado.
B11: Asignación sugerida (PM define)
B12: El PM puede dividir los 20 juniors en grupos de 4-5 por área cada semana. Rotar entre semanas. No dejar a un mismo junior siempre en la misma área (la familiaridad mata el testing exploratorio).

Sheet Resumen
B1: Resumen para el PM
B3: Por feature | H3: Por estado
B4: Feature | C4: Total | D4: Bloqueantes | E4: Graves | F4: Abiertos | H4: Estado | I4: Count
B5: Crear paciente | C5: =COUNTIF(Bugs!D:D,B5) -> 17 | D5: =COUNTIFS(Bugs!D:D,B5,Bugs!K:K,"Bloqueante") -> 0 | E5: =COUNTIFS(Bugs!D:D,B5,Bugs!K:K,"Grave") -> 0 | F5: =COUNTIFS(Bugs!D:D,B5,Bugs!L:L,"<>Arreglado",Bugs!L:L,"<>Verificado",Bugs!L:L,"<>No es bug",Bugs!L:L,"<>Duplicado",Bugs!L:L,"<>Diferido") -> 16 | H5: Nuevo | I5: =COUNTIF(Bugs!L:L,H5) -> 0
B6: Crear doctor | C6: =COUNTIF(Bugs!D:D,B6) -> 8 | D6: =COUNTIFS(Bugs!D:D,B6,Bugs!K:K,"Bloqueante") -> 0 | E6: =COUNTIFS(Bugs!D:D,B6,Bugs!K:K,"Grave") -> 0 | F6: =COUNTIFS(Bugs!D:D,B6,Bugs!L:L,"<>Arreglado",Bugs!L:L,"<>Verificado",Bugs!L:L,"<>No es bug",Bugs!L:L,"<>Duplicado",Bugs!L:L,"<>Diferido") -> 8 | H6: En revisión | I6: =COUNTIF(Bugs!L:L,H6) -> 1
B7: Calendario/Agenda | C7: =COUNTIF(Bugs!D:D,B7) -> 2 | D7: =COUNTIFS(Bugs!D:D,B7,Bugs!K:K,"Bloqueante") -> 0 | E7: =COUNTIFS(Bugs!D:D,B7,Bugs!K:K,"Grave") -> 0 | F7: =COUNTIFS(Bugs!D:D,B7,Bugs!L:L,"<>Arreglado",Bugs!L:L,"<>Verificado",Bugs!L:L,"<>No es bug",Bugs!L:L,"<>Duplicado",Bugs!L:L,"<>Diferido") -> 2 | H7: En arreglo | I7: =COUNTIF(Bugs!L:L,H7) -> 4
B8: Citas (admin) | C8: =COUNTIF(Bugs!D:D,B8) -> 7 | D8: =COUNTIFS(Bugs!D:D,B8,Bugs!K:K,"Bloqueante") -> 0 | E8: =COUNTIFS(Bugs!D:D,B8,Bugs!K:K,"Grave") -> 0 | F8: =COUNTIFS(Bugs!D:D,B8,Bugs!L:L,"<>Arreglado",Bugs!L:L,"<>Verificado",Bugs!L:L,"<>No es bug",Bugs!L:L,"<>Duplicado",Bugs!L:L,"<>Diferido") -> 7 | H8: Arreglado | I8: =COUNTIF(Bugs!L:L,H8) -> 1
B9: Retell - llamadas IA | C9: =COUNTIF(Bugs!D:D,B9) -> 0 | D9: =COUNTIFS(Bugs!D:D,B9,Bugs!K:K,"Bloqueante") -> 0 | E9: =COUNTIFS(Bugs!D:D,B9,Bugs!K:K,"Grave") -> 0 | F9: =COUNTIFS(Bugs!D:D,B9,Bugs!L:L,"<>Arreglado",Bugs!L:L,"<>Verificado",Bugs!L:L,"<>No es bug",Bugs!L:L,"<>Duplicado",Bugs!L:L,"<>Diferido") -> 0 | H9: Verificado | I9: =COUNTIF(Bugs!L:L,H9) -> 2
B10: CRM | C10: =COUNTIF(Bugs!D:D,B10) -> 27 | D10: =COUNTIFS(Bugs!D:D,B10,Bugs!K:K,"Bloqueante") -> 5 | E10: =COUNTIFS(Bugs!D:D,B10,Bugs!K:K,"Grave") -> 0 | F10: =COUNTIFS(Bugs!D:D,B10,Bugs!L:L,"<>Arreglado",Bugs!L:L,"<>Verificado",Bugs!L:L,"<>No es bug",Bugs!L:L,"<>Duplicado",Bugs!L:L,"<>Diferido") -> 18 | H10: Duplicado | I10: =COUNTIF(Bugs!L:L,H10) -> 0
B11: Historia clínica + IA | C11: =COUNTIF(Bugs!D:D,B11) -> 0 | D11: =COUNTIFS(Bugs!D:D,B11,Bugs!K:K,"Bloqueante") -> 0 | E11: =COUNTIFS(Bugs!D:D,B11,Bugs!K:K,"Grave") -> 0 | F11: =COUNTIFS(Bugs!D:D,B11,Bugs!L:L,"<>Arreglado",Bugs!L:L,"<>Verificado",Bugs!L:L,"<>No es bug",Bugs!L:L,"<>Duplicado",Bugs!L:L,"<>Diferido") -> 0 | H11: No es bug | I11: =COUNTIF(Bugs!L:L,H11) -> 4
B12: Servicios | C12: =COUNTIF(Bugs!D:D,B12) -> 2 | D12: =COUNTIFS(Bugs!D:D,B12,Bugs!K:K,"Bloqueante") -> 0 | E12: =COUNTIFS(Bugs!D:D,B12,Bugs!K:K,"Grave") -> 0 | F12: =COUNTIFS(Bugs!D:D,B12,Bugs!L:L,"<>Arreglado",Bugs!L:L,"<>Verificado",Bugs!L:L,"<>No es bug",Bugs!L:L,"<>Duplicado",Bugs!L:L,"<>Diferido") -> 2 | H12: Diferido | I12: =COUNTIF(Bugs!L:L,H12) -> 4
B13: Sales orders/Facturación | C13: =COUNTIF(Bugs!D:D,B13) -> 1 | D13: =COUNTIFS(Bugs!D:D,B13,Bugs!K:K,"Bloqueante") -> 1 | E13: =COUNTIFS(Bugs!D:D,B13,Bugs!K:K,"Grave") -> 0 | F13: =COUNTIFS(Bugs!D:D,B13,Bugs!L:L,"<>Arreglado",Bugs!L:L,"<>Verificado",Bugs!L:L,"<>No es bug",Bugs!L:L,"<>Duplicado",Bugs!L:L,"<>Diferido") -> 0 | H13: Reabierto | I13: =COUNTIF(Bugs!L:L,H13) -> 0
B14: XLS uploads/Mapping | C14: =COUNTIF(Bugs!D:D,B14) -> 0 | D14: =COUNTIFS(Bugs!D:D,B14,Bugs!K:K,"Bloqueante") -> 0 | E14: =COUNTIFS(Bugs!D:D,B14,Bugs!K:K,"Grave") -> 0 | F14: =COUNTIFS(Bugs!D:D,B14,Bugs!L:L,"<>Arreglado",Bugs!L:L,"<>Verificado",Bugs!L:L,"<>No es bug",Bugs!L:L,"<>Duplicado",Bugs!L:L,"<>Diferido") -> 0
B15: Cancel automation | C15: =COUNTIF(Bugs!D:D,B15) -> 0 | D15: =COUNTIFS(Bugs!D:D,B15,Bugs!K:K,"Bloqueante") -> 0 | E15: =COUNTIFS(Bugs!D:D,B15,Bugs!K:K,"Grave") -> 0 | F15: =COUNTIFS(Bugs!D:D,B15,Bugs!L:L,"<>Arreglado",Bugs!L:L,"<>Verificado",Bugs!L:L,"<>No es bug",Bugs!L:L,"<>Duplicado",Bugs!L:L,"<>Diferido") -> 0
B16: Web pública | C16: =COUNTIF(Bugs!D:D,B16) -> 0 | D16: =COUNTIFS(Bugs!D:D,B16,Bugs!K:K,"Bloqueante") -> 0 | E16: =COUNTIFS(Bugs!D:D,B16,Bugs!K:K,"Grave") -> 0 | F16: =COUNTIFS(Bugs!D:D,B16,Bugs!L:L,"<>Arreglado",Bugs!L:L,"<>Verificado",Bugs!L:L,"<>No es bug",Bugs!L:L,"<>Duplicado",Bugs!L:L,"<>Diferido") -> 0
B17: Otra | C17: =COUNTIF(Bugs!D:D,B17) -> 33 | D17: =COUNTIFS(Bugs!D:D,B17,Bugs!K:K,"Bloqueante") -> 0 | E17: =COUNTIFS(Bugs!D:D,B17,Bugs!K:K,"Grave") -> 0 | F17: =COUNTIFS(Bugs!D:D,B17,Bugs!L:L,"<>Arreglado",Bugs!L:L,"<>Verificado",Bugs!L:L,"<>No es bug",Bugs!L:L,"<>Duplicado",Bugs!L:L,"<>Diferido") -> 33
B18: TOTAL | C18: =SUM(C5:C17) -> 97 | D18: =SUM(D5:D17) -> 6 | E18: =SUM(E5:E17) -> 0 | F18: =SUM(F5:F17) -> 86
B22: Por tester (cuántos bugs ha reportado cada uno)
B23: Nombre | C23: Tester | D23: Bugs reportados
B24: Ejemplo | C24: JUN01 | D24: =COUNTIF(Bugs!C:C,C24) -> 1
B25: Daniel Martínez Torres | C25: DMT | D25: =COUNTIF(Bugs!C:C,C25) -> 28
B26: Randú Condori | C26: JUN03 | D26: =COUNTIF(Bugs!C:C,C26) -> 0
B27: Cristian Lalalangui | C27: JUN04 | D27: =COUNTIF(Bugs!C:C,C27) -> 0
B28: Felipe Parra Ramírez | C28: JUN05 | D28: =COUNTIF(Bugs!C:C,C28) -> 0
B29: Isamir Valencia López | C29: JUN06 | D29: =COUNTIF(Bugs!C:C,C29) -> 0
B30: Sara Estenos | C30: JUN07 | D30: =COUNTIF(Bugs!C:C,C30) -> 0
B31: Josué Zapata Ortiz | C31: JZO | D31: =COUNTIF(Bugs!C:C,C31) -> 8
B32: Diana Carolina Pita Amador | C32: JUN09 | D32: =COUNTIF(Bugs!C:C,C32) -> 0
B33: Rodrigo García Pérez | C33: RGP | D33: =COUNTIF(Bugs!C:C,C33) -> 9
B34: Josue David Real | C34: JUN11 | D34: 5
B35: Antonio Mba | C35: JUN12 | D35: =COUNTIF(Bugs!C:C,C35) -> 23
C36: JUN13 | D36: =COUNTIF(Bugs!C:C,C36) -> 0
C37: JUN14 | D37: =COUNTIF(Bugs!C:C,C37) -> 0
C38: JUN15 | D38: =COUNTIF(Bugs!C:C,C38) -> 0
C39: JUN16 | D39: =COUNTIF(Bugs!C:C,C39) -> 0
C40: JUN17 | D40: =COUNTIF(Bugs!C:C,C40) -> 0
C41: JUN18 | D41: =COUNTIF(Bugs!C:C,C41) -> 0
C42: JUN19 | D42: =COUNTIF(Bugs!C:C,C42) -> 0
C43: JUN20 | D43: =COUNTIF(Bugs!C:C,C43) -> 0

Sheet Funcionalidades
A1: # | B1: Functionality
A2: Create patient | B2: Having a user with patient role, which can be assigned to a consultation, has a medical history, can be billed an activity, can register it's own consultations
A3: Create doctor | B3: Having a user with doctor role which can have patients assigned, create and modify their medical histories, bill activities, manage his calendar,...
A4: Clinical calendar / agenda | B4: Create availability slots, monthly, weekly, daily views, click-on registers, shows KPIs, has clinic view (every doctor), doctor view(its own registers)
A5: Appointment creation by admin | B5: For every available slot, an admin can create a consultation for a patient
A6: Appointment creation by patient online in web | B6: Each patient can register and create a doctors appointment
A7: Retell | B7: We have a Retell infrastructure, we have outcoming and incoming calls by AI agents and register those with a webhook connection to Retell
A8: CRM | B8: Regular CRM with leads and contacts, we have a function that brings AI suggestions of upselling based on user history with us
A9: Clinical history with AI functions | B9: Doctor takes notes speaking and we generate the clinic history of that appointment, suggest add-ons, etc
A10: Services catalogue | B10: Create as products the different type of appointments, each with it's own duration, price, tags, doctors
A11: Sales order and invoices | B11: When a consultation is efectuated, the patient has to be billed for the service of the consult + if there are any other services that have been added during the consultation, this generates a billable order and an invoice, depending on the patient will be billed to patient or insurance company
A12: XLS uploads with active mapping | B12: in case we want to migrate a clinic database to our system, in case we need to update the prices of services from a insurance company, for this we have a mapping system where we connect xls headers to our systems ones
... A14: Cuidarles web | B14: Finish the design of the web, make everything functional
